odoo/addons/base_view_full_arch/README.rst
odoo/addons/base_view_full_arch/__init__.py
odoo/addons/base_view_full_arch/__manifest__.py
odoo/addons/base_view_full_arch/demo/ir_ui_view.xml
odoo/addons/base_view_full_arch/i18n/base_view_full_arch.pot
odoo/addons/base_view_full_arch/i18n/it.po
odoo/addons/base_view_full_arch/models/__init__.py
odoo/addons/base_view_full_arch/models/ir_ui_view.py
odoo/addons/base_view_full_arch/readme/CONTRIBUTORS.rst
odoo/addons/base_view_full_arch/readme/DESCRIPTION.rst
odoo/addons/base_view_full_arch/readme/USAGE.rst
odoo/addons/base_view_full_arch/static/description/icon.png
odoo/addons/base_view_full_arch/static/description/index.html
odoo/addons/base_view_full_arch/tests/__init__.py
odoo/addons/base_view_full_arch/tests/test_full_arch.py
odoo/addons/base_view_full_arch/tests/data/test_00_format_doc.xml
odoo/addons/base_view_full_arch/tests/data/test_01_root_view_full_arch.xml
odoo/addons/base_view_full_arch/tests/data/test_02_ancestor_view_full_arch.xml
odoo/addons/base_view_full_arch/tests/data/test_04_archive_inheriting_view.xml
odoo/addons/base_view_full_arch/tests/data/test_05_update_views_arch_propagate_top_down_ancestor_is_v1.xml
odoo/addons/base_view_full_arch/tests/data/test_05_update_views_arch_propagate_top_down_ancestor_is_v3.xml
odoo/addons/base_view_full_arch/tests/data/test_06_update_views_arch_propagate_bottom_up_ancestor_is_v1.xml
odoo/addons/base_view_full_arch/tests/data/test_06_update_views_arch_propagate_bottom_up_ancestor_is_v3.xml
odoo/addons/base_view_full_arch/views/ir_ui_view.xml
odoo14_addon_base_view_full_arch-14.0.1.0.1.dev4.dist-info/METADATA
odoo14_addon_base_view_full_arch-14.0.1.0.1.dev4.dist-info/WHEEL
odoo14_addon_base_view_full_arch-14.0.1.0.1.dev4.dist-info/top_level.txt
odoo14_addon_base_view_full_arch-14.0.1.0.1.dev4.dist-info/RECORD
