Metadata-Version: 2.1
Name: odoo14-addon-base_view_full_arch
Version: 14.0.1.0.1.dev4
Summary: Allows displaying the full, compiled architecture for all views
Home-page: https://github.com/OCA/server-tools
Author: Camptocamp,Odoo Community Association (OCA)
Author-email: support@odoo-community.org
License: LGPL-3
Classifier: Programming Language :: Python
Classifier: Framework :: Odoo
Classifier: Framework :: Odoo :: 14.0
Classifier: License :: OSI Approved :: GNU Lesser General Public License v3 (LGPLv3)
Requires-Python: >=3.6
Requires-Dist: odoo<14.1dev,>=14.0a
